{
  "project_info": {
    "project_number": "1014288671385",
    "firebase_url": "https://speechdiary.firebaseio.com",
    "project_id": "speechdiary",
    "storage_bucket": "speechdiary.appspot.com"
  },
  "client": [
    {
      "client_info": {
        "mobilesdk_app_id": "1:1014288671385:android:db68a6260753c6a1",
        "android_client_info": {
          "package_name": "com.google.cloud.android.speech"
        }
      },
      "oauth_client": [
        {
          "client_id": "1014288671385-tmh3ivg8j33r3m1crdbgtaufr2dntlvf.apps.googleusercontent.com",
          "client_type": 3
        }
      ],
      "api_key": [
        {
          "current_key": "AIzaSyCyKGdxQNk7kCCiML4PZOBMWtMvKwb7850"
        }
      ],
      "services": {
        "analytics_service": {
          "status": 1
        },
        "appinvite_service": {
          "status": 1,
          "other_platform_oauth_client": []
        },
        "ads_service": {
          "status": 2
        }
      }
    }
  ],
  "configuration_version": "1"
}